{
    "Name": "fp_techFever",
    "Enabled": true,

    "Version": "1.0.1",
    "Description": "Flashpoint taking place early 3040s",
    "Author": "Warenwolf/MRB",
	
	"DependsOn": [ "Timeline", "Mission Control", "BT_Extended_Timeline"],
	
	"DataAddendumEntries":[{ "name":"BattleTech.FactionEnumeration", "path":"enums/Faction.json", "AddToDB": true} ],
    "Manifest": [
    { "Type": "CastDef", "Path": "cast" },
	{ "Type": "BaseDescriptionDef", "Path": "descriptions" },
	{ "Type": "SimGameEventDef", "Path": "events", "AddToDB": true },
	{ "Type": "FlashpointDef", "Path": "flashpoints" },
	{ "Type": "FactionDef", "Path": "factions" },
	{ "Type": "HeraldryDef", "Path": "heraldryDef" },
	{ "Type": "ContractOverride", "Path": "contracts" },
	{ "Type": "SimGameMilestoneSet", "Path": "milestoneSets" },
	{ "Type": "SimGameConversations", "Path": "simGameConversations" },
	{ "Type": "Sprite", "Path": "sprites" },
	{ "Type": "ItemCollectionDef", "Path": "itemCollections" },
	{ "Type": "ConversationContent", "Path": "dialogue_buckets" },
	{ "Type": "PilotDef", "Path": "pilot" },
	{ "Type": "TurretDef", "Path": "turret", "AddToDB": false },
	{ "Type": "MechDef", "Path": "mech" },
	{ "Type": "AbilityDef","Path": "ability","AddToDB": false },
	{ "Type": "DialogBucketDef", "Path": "conversationBuckets" },
	{ "Type": "Texture2D",  "Path": "textures", "AddToAddendum": "ConversationTexture" }]
}
