{
	"ID": "04_fp_pm_RenegadeBattle",
	"RandomSpawns": {
		"Enable": false
	},
	"HotDropProtection": {
		"Enable": false
	},
	"AdditionalLances": {
		"Enable": false,
		"EnemyLanceCount": 1,
		"EnemyLances": [ "Damaged_Medium_Battle_Lance" ],
		"EnemyLanceObjectiveNames" : [ "Destroy Medium Lance" ],
		"HideObjective": true,
		"ShowObjectiveOnLanceDetected": false,
		"AlwaysDisplayHiddenObjectiveIfPrimary": false,
		"AllyLanceCount": 0
	},
	"ExtendedLances": {
		"Enable": false,
		"EnemyLanceSize": 6
			},
	"ExtendedBoundaries": {
		"Enable": true,
		"IncreaseBoundarySizeByPercentage": 0.2
	},
	"DynamicWithdraw": {
		"Enable": true
	},
	"AdditionalPlayerMechs": {
		"Enable": false
	}
}
